wristband/__init__.py
wristband/api.py
wristband/enums.py
wristband/fastapi/__init__.py
wristband/fastapi/auth.py
wristband/models.py
wristband/utils.py
wristband-4.3.3.dist-info/LICENSE
wristband-4.3.3.dist-info/METADATA
wristband-4.3.3.dist-info/WHEEL
wristband-4.3.3.dist-info/RECORD
